odoo8_addon_account_financial_report_webkit_xls-8.0.1.0.0-py2.7-nspkg.pth
odoo8_addon_account_financial_report_webkit_xls-8.0.1.0.0.dist-info/DESCRIPTION.rst
odoo8_addon_account_financial_report_webkit_xls-8.0.1.0.0.dist-info/METADATA
odoo8_addon_account_financial_report_webkit_xls-8.0.1.0.0.dist-info/RECORD
odoo8_addon_account_financial_report_webkit_xls-8.0.1.0.0.dist-info/WHEEL
odoo8_addon_account_financial_report_webkit_xls-8.0.1.0.0.dist-info/metadata.json
odoo8_addon_account_financial_report_webkit_xls-8.0.1.0.0.dist-info/namespace_packages.txt
odoo8_addon_account_financial_report_webkit_xls-8.0.1.0.0.dist-info/top_level.txt
odoo_addons/account_financial_report_webkit_xls/README.rst
odoo_addons/account_financial_report_webkit_xls/__init__.py
odoo_addons/account_financial_report_webkit_xls/__openerp__.py
odoo_addons/account_financial_report_webkit_xls/i18n/de.po
odoo_addons/account_financial_report_webkit_xls/i18n/es_ES.po
odoo_addons/account_financial_report_webkit_xls/i18n/fr.po
odoo_addons/account_financial_report_webkit_xls/i18n/it.po
odoo_addons/account_financial_report_webkit_xls/i18n/lt.po
odoo_addons/account_financial_report_webkit_xls/i18n/nl.po
odoo_addons/account_financial_report_webkit_xls/i18n/sl.po
odoo_addons/account_financial_report_webkit_xls/report/__init__.py
odoo_addons/account_financial_report_webkit_xls/report/aged_open_invoices_xls.py
odoo_addons/account_financial_report_webkit_xls/report/aged_partner_balance_xls.py
odoo_addons/account_financial_report_webkit_xls/report/general_ledger_xls.py
odoo_addons/account_financial_report_webkit_xls/report/open_invoices_xls.py
odoo_addons/account_financial_report_webkit_xls/report/partner_ledger_xls.py
odoo_addons/account_financial_report_webkit_xls/report/partners_balance_xls.py
odoo_addons/account_financial_report_webkit_xls/report/trial_balance_xls.py
odoo_addons/account_financial_report_webkit_xls/static/description/icon.png
odoo_addons/account_financial_report_webkit_xls/test/general_ledger.yml
odoo_addons/account_financial_report_webkit_xls/test/open_invoices.yml
odoo_addons/account_financial_report_webkit_xls/test/partner_balance.yml
odoo_addons/account_financial_report_webkit_xls/test/partner_ledger.yml
odoo_addons/account_financial_report_webkit_xls/test/trial_balance.yml
odoo_addons/account_financial_report_webkit_xls/tests/__init__.py
odoo_addons/account_financial_report_webkit_xls/tests/test_aged_open_invoices_xls.py
odoo_addons/account_financial_report_webkit_xls/tests/test_aged_partner_balance_xls.py
